lmodify/__init__.py
lmodify/cli.py
lmodify/config.py
lmodify/lmod.py
lmodify/models.py
lmodify/parser.py
lmodify/singularity.py
lmodify/commands/__init__.py
lmodify/commands/add.py
lmodify/commands/create.py
lmodify/commands/init.py
lmodify/commands/list.py
lmodify/templates/package-lua.tmpl
lmodify/templates/singularity-exec.tmpl
lmodify-0.2.1.dist-info/METADATA
lmodify-0.2.1.dist-info/WHEEL
lmodify-0.2.1.dist-info/entry_points.txt
lmodify-0.2.1.dist-info/top_level.txt
lmodify-0.2.1.dist-info/RECORD
