Metadata-Version: 2.4
Name: lmodify
Version: 0.2.1
Summary: LMODify: Create LMOD packages based on Singularity images for HPC environments
Author-email: Andrea Telatin <andrea.telatin@quadram.ac.uk>
License: MIT
Project-URL: Homepage, https://github.com/quadram-institute-bioscience/lmodify
Project-URL: Repository, https://github.com/quadram-institute-bioscience/lmodify
Project-URL: Issues, https://github.com/quadram-institute-bioscience/lmodify/issues
Classifier: Development Status :: 3 - Alpha
Classifier: Intended Audience :: Science/Research
Classifier: Intended Audience :: System Administrators
Classifier: License :: OSI Approved :: MIT License
Classifier: Programming Language :: Python :: 3
Classifier: Programming Language :: Python :: 3.10
Classifier: Programming Language :: Python :: 3.11
Classifier: Programming Language :: Python :: 3.12
Classifier: Topic :: System :: Systems Administration
Classifier: Topic :: Scientific/Engineering
Requires-Python: >=3.10
Requires-Dist: click>=8.1.0
Requires-Dist: rich>=13.0.0
Requires-Dist: rich-click>=1.7.0
Provides-Extra: dev
Requires-Dist: pytest>=7.4.0; extra == "dev"
Requires-Dist: pytest-cov>=4.1.0; extra == "dev"
